snipercorn/__main__.py
snipercorn/cli.py
snipercorn/config.py
snipercorn/sni.py
snipercorn-0.0.1.dist-info/METADATA
snipercorn-0.0.1.dist-info/WHEEL
snipercorn-0.0.1.dist-info/entry_points.txt
snipercorn-0.0.1.dist-info/RECORD