Metadata-Version: 2.0
Name: snipercorn
Version: 0.0.1
Summary: Hypercorn + Easy https:// with SNI
Home-Page: https://gitlab.com/dholth/snipercorn/
Author: Daniel Holth
Author-email: dholth@gmail.com
License: MIT
Keywords: UNKNOWN
Platform: UNKNOWN
Classifier: Development Status :: 3 - Alpha
Classifier: Environment :: Web Environment
Classifier: Intended Audience :: Developers
Classifier: License :: OSI Approved :: MIT License
Classifier: Operating System :: OS Independent
Classifier: Programming Language :: Python
Classifier: Programming Language :: Python :: 3
Classifier: Programming Language :: Python :: 3.7
Classifier: Topic :: Internet :: WWW/HTTP :: Dynamic Content
Classifier: Topic :: Software Development :: Libraries :: Python Modules
Requires-Dist: hypercorn
Requires-Dist: appdirs
Requires-Dist: click
